crazylibs/__init__.py
crazylibs/__main__.py
crazylibs/cli.py
crazylibs/py.typed
crazylibs/stories/__init__.py
crazylibs/stories/_story.py
crazylibs/stories/a_day_at_the_zoo.py
crazylibs-0.1.2.dist-info/LICENSE
crazylibs-0.1.2.dist-info/METADATA
crazylibs-0.1.2.dist-info/WHEEL
crazylibs-0.1.2.dist-info/top_level.txt
crazylibs-0.1.2.dist-info/RECORD
